amplify/__init__.py
amplify/__init__.pyi
amplify/_backward.py
amplify/amplify.cpython-310-darwin.so
amplify/constraint.py
amplify/py.typed
amplify/client/__init__.py
amplify/client/ocean.py
amplify-1.4.1.dist-info/licenses/LICENSE.txt
amplify-1.4.1.dist-info/licenses/open_source_license.txt
amplify-1.4.1.dist-info/METADATA
amplify-1.4.1.dist-info/WHEEL
amplify-1.4.1.dist-info/top_level.txt
amplify-1.4.1.dist-info/RECORD
