Metadata-Version: 2.4
Name: amplify
Version: 1.4.1
Summary: Amplify SDK for Quantum Annealing and Ising Machines
Author-email: "Fixstars Amplify Corp." <y_matsuda@fixstars.com>
Maintainer-email: Yoshiki Matsuda <y_matsuda@fixstars.com>
License-Expression: LicenseRef-Fixstars-Amplify-SDK-2023-03-17
Project-URL: Homepage, https://amplify.fixstars.com/
Project-URL: Documentation, https://amplify.fixstars.com/docs/amplify/v1/
Project-URL: Changelog, https://amplify.fixstars.com/docs/amplify/v1/changelog.html
Project-URL: Tutorial, https://amplify.fixstars.com/demo
Keywords: quantum,quantum annealing,annealer,annealing machine,QUBO,quadratic unconstrained binary optimization,d-wave,digital annealer,sdk,sbm,simulated bifurcation,simulated annealing,Ising machine,Ising model,fixstars,fixstars amplify
Classifier: Environment :: Console
Classifier: Development Status :: 5 - Production/Stable
Classifier: Intended Audience :: Developers
Classifier: Intended Audience :: Science/Research
Classifier: Topic :: Software Development :: Libraries :: Python Modules
Classifier: Topic :: Scientific/Engineering
Classifier: Operating System :: POSIX :: Linux
Classifier: Operating System :: Microsoft :: Windows
Classifier: Operating System :: MacOS :: MacOS X
Classifier: Programming Language :: C++
Classifier: Programming Language :: Python :: 3.10
Classifier: Programming Language :: Python :: 3.11
Classifier: Programming Language :: Python :: 3.12
Classifier: Programming Language :: Python :: 3.13
Classifier: Programming Language :: Python :: 3.14
Requires-Python: >=3.10
License-File: LICENSE.txt
License-File: open_source_license.txt
Requires-Dist: numpy!=1.24.0
Requires-Dist: typing-extensions
Provides-Extra: extra
Requires-Dist: dwave-system>=1.33.0; extra == "extra"
Dynamic: license-file
